{
  "contributors": null,
  "coordinates": null,
  "created_at": "Sat Jul 13 11:56:33 +0000 2019",
  "display_text_range": [
    0,
    187
  ],
  "entities": {
    "hashtags": [],
    "symbols": [],
    "urls": [
      {
        "display_url": "twitter.com/JudicialWatch/\u2026",
        "expanded_url": "https://twitter.com/JudicialWatch/status/1149883648373477378",
        "indices": [
          188,
          211
        ],
        "url": "https://t.co/bHweiBBj7z"
      }
    ],
    "user_mentions": []
  },
  "favorite_count": 55732,
  "favorited": false,
  "full_text": "Andy McCabe is a major sleazebag. Among many other things, he took massive amounts of money from Crooked Hillary reps, for wife\u2019s campaign, while Hillary was under \u201cinvestigation\u201d by FBI! https://t.co/bHweiBBj7z",
  "geo": null,
  "id": 1150011125347627009,
  "id_str": "1150011125347627009",
  "in_reply_to_screen_name": null,
  "in_reply_to_status_id": null,
  "in_reply_to_status_id_str": null,
  "in_reply_to_user_id": null,
  "in_reply_to_user_id_str": null,
  "is_quote_status": true,
  "lang": "en",
  "place": null,
  "possibly_sensitive": false,
  "quoted_status": {
    "contributors": null,
    "coordinates": null,
    "created_at": "Sat Jul 13 03:30:00 +0000 2019",
    "display_text_range": [
      0,
      268
    ],
    "entities": {
      "hashtags": [],
      "symbols": [],
      "urls": [
        {
          "display_url": "jwatch.us/cbZAF3",
          "expanded_url": "http://jwatch.us/cbZAF3",
          "indices": [
            245,
            268
          ],
          "url": "https://t.co/DbXXJvQsgS"
        }
      ],
      "user_mentions": []
    },
    "favorite_count": 16986,
    "favorited": false,
    "full_text": "JW announced that it filed a FOIA lawsuit against the DOJ for records of communications between the FBI &amp; former FBI Deputy Director Andrew McCabe related to his book, The Threat: How the FBI Protects America in the Age of Terror and Trump. https://t.co/DbXXJvQsgS",
    "geo": null,
    "id": 1149883648373477378,
    "id_str": "1149883648373477378",
    "in_reply_to_screen_name": null,
    "in_reply_to_status_id": null,
    "in_reply_to_status_id_str": null,
    "in_reply_to_user_id": null,
    "in_reply_to_user_id_str": null,
    "is_quote_status": false,
    "lang": "en",
    "place": null,
    "possibly_sensitive": false,
    "retweet_count": 5660,
    "retweeted": false,
    "source": "<a href=\"https://about.twitter.com/products/tweetdeck\" rel=\"nofollow\">TweetDeck</a>",
    "truncated": false,
    "user": {
      "contributors_enabled": false,
      "created_at": "Fri Dec 19 18:04:57 +0000 2008",
      "default_profile": false,
      "default_profile_image": false,
      "description": "A conservative non-partisan educational foundation promoting transparency, accountability, & integrity in government. Follow us on FB & Instagram: judicialwatch",
      "entities": {
        "description": {
          "urls": []
        },
        "url": {
          "urls": [
            {
              "display_url": "judicialwatch.org",
              "expanded_url": "http://www.judicialwatch.org",
              "indices": [
                0,
                23
              ],
              "url": "https://t.co/JPjqvKy5es"
            }
          ]
        }
      },
      "favourites_count": 1450,
      "follow_request_sent": false,
      "followers_count": 1150360,
      "following": false,
      "friends_count": 1960,
      "geo_enabled": true,
      "has_extended_profile": false,
      "id": 18247062,
      "id_str": "18247062",
      "is_translation_enabled": false,
      "is_translator": false,
      "lang": null,
      "listed_count": 5206,
      "location": "Washington, DC",
      "name": "Judicial Watch \ud83d\udd0e",
      "notifications": false,
      "profile_background_color": "ABB8C2",
      "profile_background_image_url": "http://abs.twimg.com/images/themes/theme1/bg.png",
      "profile_background_image_url_https": "https://abs.twimg.com/images/themes/theme1/bg.png",
      "profile_background_tile": true,
      "profile_banner_url": "https://pbs.twimg.com/profile_banners/18247062/1557862227",
      "profile_image_url": "http://pbs.twimg.com/profile_images/1149693510301429760/tqrvTBTF_normal.png",
      "profile_image_url_https": "https://pbs.twimg.com/profile_images/1149693510301429760/tqrvTBTF_normal.png",
      "profile_link_color": "1B95E0",
      "profile_sidebar_border_color": "000000",
      "profile_sidebar_fill_color": "EEEEEE",
      "profile_text_color": "30353B",
      "profile_use_background_image": false,
      "protected": false,
      "screen_name": "JudicialWatch",
      "statuses_count": 62608,
      "time_zone": null,
      "translator_type": "none",
      "url": "https://t.co/JPjqvKy5es",
      "utc_offset": null,
      "verified": true
    }
  },
  "quoted_status_id": 1149883648373477378,
  "quoted_status_id_str": "1149883648373477378",
  "quoted_status_permalink": {
    "display": "twitter.com/JudicialWatch/\u2026",
    "expanded": "https://twitter.com/JudicialWatch/status/1149883648373477378",
    "url": "https://t.co/bHweiBBj7z"
  },
  "retweet_count": 17417,
  "retweeted": false,
  "source": "<a href=\"http://twitter.com/download/iphone\" rel=\"nofollow\">Twitter for iPhone</a>",
  "truncated": false,
  "user": {
    "contributors_enabled": false,
    "created_at": "Wed Mar 18 13:46:38 +0000 2009",
    "default_profile": false,
    "default_profile_image": false,
    "description": "45th President of the United States of America\ud83c\uddfa\ud83c\uddf8",
    "entities": {
      "description": {
        "urls": []
      },
      "url": {
        "urls": [
          {
            "display_url": "Instagram.com/realDonaldTrump",
            "expanded_url": "http://www.Instagram.com/realDonaldTrump",
            "indices": [
              0,
              23
            ],
            "url": "https://t.co/OMxB0x7xC5"
          }
        ]
      }
    },
    "favourites_count": 8,
    "follow_request_sent": false,
    "followers_count": 61896633,
    "following": true,
    "friends_count": 47,
    "geo_enabled": true,
    "has_extended_profile": false,
    "id": 25073877,
    "id_str": "25073877",
    "is_translation_enabled": true,
    "is_translator": false,
    "lang": null,
    "listed_count": 105215,
    "location": "Washington, DC",
    "name": "Donald J. Trump",
    "notifications": false,
    "profile_background_color": "6D5C18",
    "profile_background_image_url": "http://abs.twimg.com/images/themes/theme1/bg.png",
    "profile_background_image_url_https": "https://abs.twimg.com/images/themes/theme1/bg.png",
    "profile_background_tile": true,
    "profile_banner_url": "https://pbs.twimg.com/profile_banners/25073877/1560920145",
    "profile_image_url": "http://pbs.twimg.com/profile_images/874276197357596672/kUuht00m_normal.jpg",
    "profile_image_url_https": "https://pbs.twimg.com/profile_images/874276197357596672/kUuht00m_normal.jpg",
    "profile_link_color": "1B95E0",
    "profile_sidebar_border_color": "BDDCAD",
    "profile_sidebar_fill_color": "C5CEC0",
    "profile_text_color": "333333",
    "profile_use_background_image": true,
    "protected": false,
    "screen_name": "realDonaldTrump",
    "statuses_count": 42901,
    "time_zone": null,
    "translator_type": "regular",
    "url": "https://t.co/OMxB0x7xC5",
    "utc_offset": null,
    "verified": true
  }
}