{
  "contributors": null,
  "coordinates": null,
  "created_at": "Fri Jan 10 13:36:12 +0000 2020",
  "display_text_range": [
    0,
    140
  ],
  "entities": {
    "hashtags": [],
    "symbols": [],
    "urls": [],
    "user_mentions": [
      {
        "id": 19726613,
        "id_str": "19726613",
        "indices": [
          3,
          18
        ],
        "name": "Sen. Susan Collins",
        "screen_name": "SenatorCollins"
      }
    ]
  },
  "favorite_count": 0,
  "favorited": false,
  "full_text": "RT @SenatorCollins: Since 2016, Congress has boosted funding to address the opioid epidemic by 1,300 percent. To ensure those struggling wi\u2026",
  "geo": null,
  "id": 1215628407209431040,
  "id_str": "1215628407209431040",
  "in_reply_to_screen_name": null,
  "in_reply_to_status_id": null,
  "in_reply_to_status_id_str": null,
  "in_reply_to_user_id": null,
  "in_reply_to_user_id_str": null,
  "is_quote_status": false,
  "lang": "en",
  "place": null,
  "retweet_count": 3786,
  "retweeted": false,
  "retweeted_status": {
    "contributors": null,
    "coordinates": null,
    "created_at": "Thu Jan 09 15:47:25 +0000 2020",
    "display_text_range": [
      0,
      276
    ],
    "entities": {
      "hashtags": [],
      "symbols": [],
      "urls": [],
      "user_mentions": []
    },
    "favorite_count": 15571,
    "favorited": false,
    "full_text": "Since 2016, Congress has boosted funding to address the opioid epidemic by 1,300 percent. To ensure those struggling with addiction are able to access the treatment they need, we must increase the number of providers to keep pace with the billions of dollars in new resources.",
    "geo": null,
    "id": 1215299040641941505,
    "id_str": "1215299040641941505",
    "in_reply_to_screen_name": null,
    "in_reply_to_status_id": null,
    "in_reply_to_status_id_str": null,
    "in_reply_to_user_id": null,
    "in_reply_to_user_id_str": null,
    "is_quote_status": false,
    "lang": "en",
    "place": null,
    "retweet_count": 3786,
    "retweeted": false,
    "source": "<a href=\"https://mobile.twitter.com\" rel=\"nofollow\">Twitter Web App</a>",
    "truncated": false,
    "user": {
      "can_media_tag": true,
      "contributors_enabled": false,
      "created_at": "Thu Jan 29 18:56:59 +0000 2009",
      "default_profile": false,
      "default_profile_image": false,
      "description": "United States Senator from Maine. \r\n\r\nAll tweets originate from the Press Office of Senator Susan Collins.",
      "entities": {
        "description": {
          "urls": []
        },
        "url": {
          "urls": [
            {
              "display_url": "collins.senate.gov",
              "expanded_url": "http://collins.senate.gov",
              "indices": [
                0,
                22
              ],
              "url": "http://t.co/GC3gCGTqQX"
            }
          ]
        }
      },
      "favourites_count": 76,
      "follow_request_sent": false,
      "followed_by": false,
      "followers_count": 520031,
      "following": false,
      "friends_count": 971,
      "geo_enabled": true,
      "has_extended_profile": false,
      "id": 19726613,
      "id_str": "19726613",
      "is_translation_enabled": false,
      "is_translator": false,
      "lang": null,
      "listed_count": 4435,
      "location": "Maine",
      "name": "Sen. Susan Collins",
      "notifications": false,
      "profile_background_color": "FFFFFF",
      "profile_background_image_url": "http://abs.twimg.com/images/themes/theme1/bg.png",
      "profile_background_image_url_https": "https://abs.twimg.com/images/themes/theme1/bg.png",
      "profile_background_tile": false,
      "profile_banner_url": "https://pbs.twimg.com/profile_banners/19726613/1526569711",
      "profile_image_url": "http://pbs.twimg.com/profile_images/588697537013383168/Kf_x_1u1_normal.jpg",
      "profile_image_url_https": "https://pbs.twimg.com/profile_images/588697537013383168/Kf_x_1u1_normal.jpg",
      "profile_link_color": "516C87",
      "profile_sidebar_border_color": "FFFFFF",
      "profile_sidebar_fill_color": "C7D9ED",
      "profile_text_color": "192F45",
      "profile_use_background_image": true,
      "protected": false,
      "screen_name": "SenatorCollins",
      "statuses_count": 3294,
      "time_zone": null,
      "translator_type": "none",
      "url": "http://t.co/GC3gCGTqQX",
      "utc_offset": null,
      "verified": true
    }
  },
  "source": "<a href=\"http://twitter.com/download/iphone\" rel=\"nofollow\">Twitter for iPhone</a>",
  "truncated": false,
  "user": {
    "can_media_tag": false,
    "contributors_enabled": false,
    "created_at": "Wed Mar 18 13:46:38 +0000 2009",
    "default_profile": false,
    "default_profile_image": false,
    "description": "45th President of the United States of America\ud83c\uddfa\ud83c\uddf8",
    "entities": {
      "description": {
        "urls": []
      },
      "url": {
        "urls": [
          {
            "display_url": "Instagram.com/realDonaldTrump",
            "expanded_url": "http://www.Instagram.com/realDonaldTrump",
            "indices": [
              0,
              23
            ],
            "url": "https://t.co/OMxB0x7xC5"
          }
        ]
      }
    },
    "favourites_count": 6,
    "follow_request_sent": false,
    "followed_by": false,
    "followers_count": 70645362,
    "following": true,
    "friends_count": 47,
    "geo_enabled": true,
    "has_extended_profile": false,
    "id": 25073877,
    "id_str": "25073877",
    "is_translation_enabled": true,
    "is_translator": false,
    "lang": null,
    "listed_count": 113128,
    "location": "Washington, DC",
    "name": "Donald J. Trump",
    "notifications": false,
    "profile_background_color": "6D5C18",
    "profile_background_image_url": "http://abs.twimg.com/images/themes/theme1/bg.png",
    "profile_background_image_url_https": "https://abs.twimg.com/images/themes/theme1/bg.png",
    "profile_background_tile": true,
    "profile_banner_url": "https://pbs.twimg.com/profile_banners/25073877/1560920145",
    "profile_image_url": "http://pbs.twimg.com/profile_images/874276197357596672/kUuht00m_normal.jpg",
    "profile_image_url_https": "https://pbs.twimg.com/profile_images/874276197357596672/kUuht00m_normal.jpg",
    "profile_link_color": "1B95E0",
    "profile_sidebar_border_color": "BDDCAD",
    "profile_sidebar_fill_color": "C5CEC0",
    "profile_text_color": "333333",
    "profile_use_background_image": true,
    "protected": false,
    "screen_name": "realDonaldTrump",
    "statuses_count": 47812,
    "time_zone": null,
    "translator_type": "regular",
    "url": "https://t.co/OMxB0x7xC5",
    "utc_offset": null,
    "verified": true
  }
}